goblet_workflows/__init__.py
goblet_workflows/__version__.py
goblet_workflows/cli.py
goblet_workflows/client.py
goblet_workflows/controls.py
goblet_workflows/exceptions.py
goblet_workflows/steps.py
goblet_workflows/utils.py
goblet_workflows/workflow.py
goblet_workflows-0.1.4.dist-info/LICENSE
goblet_workflows-0.1.4.dist-info/METADATA
goblet_workflows-0.1.4.dist-info/WHEEL
goblet_workflows-0.1.4.dist-info/entry_points.txt
goblet_workflows-0.1.4.dist-info/top_level.txt
goblet_workflows-0.1.4.dist-info/RECORD
