Metadata-Version: 2.1
Name: goblet-workflows
Version: 0.1.4
Summary: Google Cloud Workflows wrapper
Home-page: https://github.com/goblet/goblet_workflows
Author: Austen
Author-email: austen.novis@gmail.com
License: MIT
Platform: UNKNOWN
Classifier: License :: OSI Approved :: MIT License
Classifier: Programming Language :: Python
Classifier: Programming Language :: Python :: 3
Classifier: Programming Language :: Python :: 3.8
Classifier: Programming Language :: Python :: 3.9
Classifier: Programming Language :: Python :: 3.10
Classifier: Programming Language :: Python :: Implementation :: CPython
Classifier: Programming Language :: Python :: Implementation :: PyPy
Requires-Python: >=3.8.0
License-File: LICENSE
Requires-Dist: click
Requires-Dist: google-api-python-client
Requires-Dist: ruamel.yaml
Requires-Dist: polling2
Requires-Dist: goblet-gcp-client
